datatransformtoolbox/__init__.py
datatransformtoolbox/crosscorrelation/__init__.py
datatransformtoolbox/crosscorrelation/api.py
datatransformtoolbox/crosscorrelation/core.py
datatransformtoolbox/transpose/__init__.py
datatransformtoolbox/transpose/api.py
datatransformtoolbox/transpose/core.py
datatransformtoolbox/window/__init__.py
datatransformtoolbox/window/api.py
datatransformtoolbox/window/core.py
datatransformtoolbox-0.1.5.dist-info/LICENSE
datatransformtoolbox-0.1.5.dist-info/METADATA
datatransformtoolbox-0.1.5.dist-info/WHEEL
datatransformtoolbox-0.1.5.dist-info/RECORD
